featurewiz/__init__.py
featurewiz/__version__.py
featurewiz/auto_encoders.py
featurewiz/blagging.py
featurewiz/classify_method.py
featurewiz/databunch.py
featurewiz/encoders.py
featurewiz/featurewiz.py
featurewiz/ml_models.py
featurewiz/my_encoders.py
featurewiz/settings.py
featurewiz/stacking_models.py
featurewiz/sulov_method.py
featurewiz-0.6.1.dist-info/LICENSE
featurewiz-0.6.1.dist-info/METADATA
featurewiz-0.6.1.dist-info/WHEEL
featurewiz-0.6.1.dist-info/top_level.txt
featurewiz-0.6.1.dist-info/RECORD
