Metadata-Version: 2.2
Name: featurewiz
Version: 0.6.1
Summary: Select Best Features from your data set - any size - now with XGBoost!
Home-page: https://github.com/AutoViML/featurewiz
Author: Ram Seshadri
Author-email: rsesha2001@yahoo.com
License: Apache License 2.0
Classifier: Programming Language :: Python :: 3
Classifier: Operating System :: OS Independent
License-File: LICENSE
Requires-Dist: numpy<2.0
Requires-Dist: ipython
Requires-Dist: jupyter
Requires-Dist: xgboost<=1.7.6,>=1.6.2
Requires-Dist: pandas>=2.0
Requires-Dist: matplotlib
Requires-Dist: seaborn
Requires-Dist: scipy
Requires-Dist: scikit-learn<=1.5.2,>=1.2.2
Requires-Dist: networkx
Requires-Dist: category_encoders==2.6.3
Requires-Dist: xlrd>=2.0.0
Requires-Dist: dask>=2021.11.0
Requires-Dist: lightgbm>=3.2.1
Requires-Dist: distributed>=2021.11.0
Requires-Dist: feather-format>=0.4.1
Requires-Dist: pyarrow>=7.0.0
Requires-Dist: fsspec>=0.3.3
Requires-Dist: Pillow>=9.0.0
Requires-Dist: tqdm>=4.61.1
Requires-Dist: numexpr>=2.7.3
Requires-Dist: tensorflow>=2.5.2
Requires-Dist: lazytransform>=1.17
Dynamic: author
Dynamic: author-email
Dynamic: classifier
Dynamic: description
Dynamic: description-content-type
Dynamic: home-page
Dynamic: license
Dynamic: requires-dist
Dynamic: summary
